pypalex/Extractor.py
pypalex/__init__.py
pypalex/__main__.py
pypalex/arg_messages.py
pypalex/constants.py
pypalex/conversion_utils.py
pypalex/extraction_utils.py
pypalex/file_utils.py
pypalex/image_utils.py
pypalex/print_utils.py
pypalex/settings.py
pypalex-2.2.2.dist-info/LICENSE
pypalex-2.2.2.dist-info/METADATA
pypalex-2.2.2.dist-info/WHEEL
pypalex-2.2.2.dist-info/entry_points.txt
pypalex-2.2.2.dist-info/top_level.txt
pypalex-2.2.2.dist-info/RECORD
