Metadata-Version: 2.1
Name: pypalex
Version: 2.2.2
Summary: Python Palette Extractor: extracts color palettes from images into json / yaml files.
Home-page: https://github.com/AlTimofeyev/pypalex
Author: Al Timofeyev
Author-email: al.timofeyev@outlook.com
License: MIT
Download-URL: https://github.com/AlTimofeyev/pypalex/archive/2.2.2.tar.gz
Project-URL: Changelog, https://github.com/AlTimofeyev/pypalex/blob/main/CHANGELOG.md
Project-URL: Documentation, https://github.com/AlTimofeyev/pypalex/blob/main/pypalex_code_documentation.pdf
Project-URL: Wiki, https://github.com/AlTimofeyev/pypalex/wiki
Project-URL: Showcase, https://github.com/AlTimofeyev/pypalex/wiki/Archive-of-Palette-Examples
Keywords: python,pypalex,palex,color-palette,colorscheme,extract-colorscheme,extract-palette,extractor
Platform: UNKNOWN
Classifier: Environment :: X11 Applications
Classifier: License :: OSI Approved :: MIT License
Classifier: Operating System :: MacOS
Classifier: Operating System :: POSIX :: Linux
Classifier: Operating System :: Microsoft :: Windows
Classifier: Operating System :: OS Independent
Classifier: Programming Language :: Python :: 3.6
Classifier: Programming Language :: Python :: 3.7
Classifier: Programming Language :: Python :: 3.8
Classifier: Programming Language :: Python :: 3.9
Requires-Python: >=3.6
License-File: LICENSE
Requires-Dist: pillow>=9.0
Requires-Dist: numpy>=1.21
Requires-Dist: filetype>=1.0
Requires-Dist: PyYAML>=5.4.1
